client_report/__init__.py
client_report/__main__.py
client_report/report.py
client_report_sk24-0.1.0.dist-info/METADATA
client_report_sk24-0.1.0.dist-info/WHEEL
client_report_sk24-0.1.0.dist-info/entry_points.txt
client_report_sk24-0.1.0.dist-info/top_level.txt
client_report_sk24-0.1.0.dist-info/RECORD
