Metadata-Version: 2.1
Name: client-report-sk24
Version: 0.1.0
Summary: Пакет для составления отчёта по клиентам
Author-email: Stanislav Kuleshov <phtschmth171@gmail.com>
